README.md
setup.py
looptools/__init__.py
looptools/_version.py
looptools/chunks.py
looptools/counter.py
looptools/log.py
looptools/timer.py
looptools.egg-info/PKG-INFO
looptools.egg-info/SOURCES.txt
looptools.egg-info/dependency_links.txt
looptools.egg-info/top_level.txt