Metadata-Version: 1.0
Name: looptools
Version: 1.2.3
Summary: Lightweight Python help utility.
Home-page: https://github.com/mrstephenneal/looptools
Author: Stephen Neal
Author-email: stephen@stephenneal.net
License: MIT Licence
Platform: UNKNOWN
